whisper_blog_admin-0.0.6-py3.9-nspkg.pth
whisper/admin/__init__.py
whisper/admin/admin.py
whisper/admin/config.py
whisper/admin/py.typed
whisper/admin/auth/__init__.py
whisper/admin/auth/cookie.py
whisper/admin/auth/dummy.py
whisper/admin/auth/ip.py
whisper/admin/auth/password.py
whisper/admin/auth/totp.py
whisper/admin/auth/webauthn.py
whisper/admin/static/admin.css
whisper/admin/static/admin.js
whisper/admin/static/auth.css
whisper/admin/static/auth.js
whisper/admin/static/common.css
whisper/admin/static/post.css
whisper/admin/static/post.js
whisper/admin/template/admin.html
whisper/admin/template/auth.html
whisper/admin/template/base.html
whisper/admin/template/post.html
whisper_blog_admin-0.0.6.dist-info/LICENSE
whisper_blog_admin-0.0.6.dist-info/METADATA
whisper_blog_admin-0.0.6.dist-info/WHEEL
whisper_blog_admin-0.0.6.dist-info/namespace_packages.txt
whisper_blog_admin-0.0.6.dist-info/top_level.txt
whisper_blog_admin-0.0.6.dist-info/RECORD
